Metadata-Version: 2.1
Name: linearregressor
Version: 0.0.1
Summary: Module of numerical statistic prediction using linear regression by determinant matrix method with intercept, slope, correlation coefficient, and determination coefficient calculations
Home-page: https://github.com/zaafirrahman/linearregressor
Author: Zaafirrahman
Author-email: zaafir123rahman@gmail.com
License: MIT
Keywords: linear regression,machine learning,prediction
Platform: UNKNOWN
Classifier: Development Status :: 5 - Production/Stable
Classifier: Intended Audience :: Information Technology
Classifier: Intended Audience :: Science/Research
Classifier: Operating System :: OS Independent
Classifier: License :: OSI Approved :: MIT License
Classifier: Programming Language :: Python :: 3
